videosdk/plugins/murfai/__init__.py
videosdk/plugins/murfai/tts.py
videosdk/plugins/murfai/version.py
videosdk_plugins_murfai-0.0.58.dist-info/METADATA
videosdk_plugins_murfai-0.0.58.dist-info/WHEEL
videosdk_plugins_murfai-0.0.58.dist-info/RECORD
